wraplab.cp39-win_amd64.pyd
wraplab-0.0.1.dist-info/METADATA
wraplab-0.0.1.dist-info/WHEEL
wraplab-0.0.1.dist-info/top_level.txt
wraplab-0.0.1.dist-info/RECORD
