Metadata-Version: 2.1
Name: wraplab
Version: 0.0.1
Summary: A test project using pybind11
Home-page: https://github.com/marcosalvalaggio-bip/cpp-study
Author: Marco Salvalaggio
Author-email: mar.salvalaggio@gmail.com
Requires-Python: >=3.7
Provides-Extra: test
Requires-Dist: pytest ; extra == 'test'
